{
  "collapse-filter": false,
  "search": "",
  "showTags": false,
  "showAttachments": false,
  "hideUnresolved": false,
  "showOrphans": true,
  "collapse-color-groups": true,
  "colorGroups": [
    {
      "query": "path:CSCC37  ",
      "color": {
        "a": 1,
        "rgb": 14701138
      }
    },
    {
      "query": "path:CSCC73  ",
      "color": {
        "a": 1,
        "rgb": 14725458
      }
    },
    {
      "query": "path:CSCC10 ",
      "color": {
        "a": 1,
        "rgb": 11657298
      }
    },
    {
      "query": "path:CSCC43",
      "color": {
        "a": 1,
        "rgb": 5431378
      }
    }
  ],
  "collapse-display": false,
  "showArrow": true,
  "textFadeMultiplier": -3,
  "nodeSizeMultiplier": 1.77208364591148,
  "lineSizeMultiplier": 2.28671230307577,
  "collapse-forces": false,
  "centerStrength": 0.353244561140285,
  "repelStrength": 15.5870217554389,
  "linkStrength": 1,
  "linkDistance": 360,
  "scale": 0.25898217050236017,
  "close": true
}